odoo/addons/account_statement_base/README.rst
odoo/addons/account_statement_base/__init__.py
odoo/addons/account_statement_base/__manifest__.py
odoo/addons/account_statement_base/i18n/account_statement_base.pot
odoo/addons/account_statement_base/i18n/es.po
odoo/addons/account_statement_base/i18n/fr.po
odoo/addons/account_statement_base/i18n/it.po
odoo/addons/account_statement_base/i18n/lv.po
odoo/addons/account_statement_base/i18n/pt_BR.po
odoo/addons/account_statement_base/i18n/tr.po
odoo/addons/account_statement_base/i18n/zh.po
odoo/addons/account_statement_base/i18n/zh_CN.po
odoo/addons/account_statement_base/models/__init__.py
odoo/addons/account_statement_base/models/account_bank_statement.py
odoo/addons/account_statement_base/models/account_bank_statement_line.py
odoo/addons/account_statement_base/models/account_journal_dashboard.py
odoo/addons/account_statement_base/readme/CONTRIBUTORS.md
odoo/addons/account_statement_base/readme/CREDITS.md
odoo/addons/account_statement_base/readme/DESCRIPTION.md
odoo/addons/account_statement_base/static/description/icon.png
odoo/addons/account_statement_base/static/description/index.html
odoo/addons/account_statement_base/tests/__init__.py
odoo/addons/account_statement_base/tests/test_account_statement_base.py
odoo/addons/account_statement_base/views/account_bank_statement.xml
odoo/addons/account_statement_base/views/account_bank_statement_line.xml
odoo_addon_account_statement_base-19.0.1.0.0.2.dist-info/METADATA
odoo_addon_account_statement_base-19.0.1.0.0.2.dist-info/WHEEL
odoo_addon_account_statement_base-19.0.1.0.0.2.dist-info/top_level.txt
odoo_addon_account_statement_base-19.0.1.0.0.2.dist-info/RECORD
